[
    {
        "epoch": 0,
        "n_train": 48,
        "n_val": 3,
        "ns_start": 3395504715021,
        "ns_end": 3395814251794,
        "train_loss": 52.815067768096924,
        "val_loss": 3.2962028980255127,
        "train_precision": 0.3061686297074932,
        "train_recall": 0.333125,
        "train_f1": 0.2512345847818133,
        "val_precision": 0.2373841429369067,
        "val_recall": 0.405,
        "val_f1": 0.23593362195891468
    },
    {
        "epoch": 1,
        "n_train": 48,
        "n_val": 3,
        "ns_start": 3395830732623,
        "ns_end": 3396140626421,
        "train_loss": 52.7430454492569,
        "val_loss": 3.296134114265442,
        "train_precision": 0.21559160416303272,
        "train_recall": 0.3446875,
        "train_f1": 0.17973744221879812,
        "val_precision": 0.2373841429369067,
        "val_recall": 0.405,
        "val_f1": 0.23593362195891468
    },
    {
        "epoch": 2,
        "n_train": 48,
        "n_val": 3,
        "ns_start": 3396156906902,
        "ns_end": 3396465162358,
        "train_loss": 52.73769569396973,
        "val_loss": 3.297090172767639,
        "train_precision": 0.14860604653736886,
        "train_recall": 0.34375,
        "train_f1": 0.17758762056033736,
        "val_precision": 0.2373841429369067,
        "val_recall": 0.405,
        "val_f1": 0.23593362195891468
    },
    {
        "epoch": 3,
        "n_train": 48,
        "n_val": 3,
        "ns_start": 3396481334629,
        "ns_end": 3396793477266,
        "train_loss": 52.7316632270813,
        "val_loss": 3.29468309879303,
        "train_precision": 0.20893063388095148,
        "train_recall": 0.340625,
        "train_f1": 0.1938848265602829,
        "val_precision": 0.16267777777777778,
        "val_recall": 0.4033333333333333,
        "val_f1": 0.23184481393507525
    },
    {
        "epoch": 4,
        "n_train": 48,
        "n_val": 3,
        "ns_start": 3396809064165,
        "ns_end": 3397120036025,
        "train_loss": 52.72671675682068,
        "val_loss": 3.2957534790039062,
        "train_precision": 0.2136422680074951,
        "train_recall": 0.34125,
        "train_f1": 0.1919299471940366,
        "val_precision": 0.16267777777777778,
        "val_recall": 0.4033333333333333,
        "val_f1": 0.23184481393507525
    },
    {
        "epoch": 5,
        "n_train": 48,
        "n_val": 3,
        "ns_start": 3397135683315,
        "ns_end": 3397443973337,
        "train_loss": 52.718541741371155,
        "val_loss": 3.2964539527893066,
        "train_precision": 0.24285561761884375,
        "train_recall": 0.3461458333333333,
        "train_f1": 0.18600970875020378,
        "val_precision": 0.16267777777777778,
        "val_recall": 0.4033333333333333,
        "val_f1": 0.23184481393507525
    },
    {
        "epoch": 6,
        "n_train": 48,
        "n_val": 3,
        "ns_start": 3397459666333,
        "ns_end": 3397760659952,
        "train_loss": 52.71109116077423,
        "val_loss": 3.2942346334457397,
        "train_precision": 0.251363326677216,
        "train_recall": 0.3488541666666667,
        "train_f1": 0.2036462129201714,
        "val_precision": 0.16267777777777778,
        "val_recall": 0.4033333333333333,
        "val_f1": 0.23184481393507525
    },
    {
        "epoch": 7,
        "n_train": 48,
        "n_val": 3,
        "ns_start": 3397776400098,
        "ns_end": 3398089188614,
        "train_loss": 52.68509328365326,
        "val_loss": 3.29157030582428,
        "train_precision": 0.2460504853151024,
        "train_recall": 0.35104166666666664,
        "train_f1": 0.24273661243113584,
        "val_precision": 0.38461602671118533,
        "val_recall": 0.405,
        "val_f1": 0.2354289491898415
    },
    {
        "epoch": 8,
        "n_train": 48,
        "n_val": 3,
        "ns_start": 3398105011136,
        "ns_end": 3398417001008,
        "train_loss": 52.61043047904968,
        "val_loss": 3.2836884260177612,
        "train_precision": 0.26274697185537266,
        "train_recall": 0.37447916666666664,
        "train_f1": 0.27994752033901765,
        "val_precision": 0.611291962174941,
        "val_recall": 0.4083333333333333,
        "val_f1": 0.26553908310581165
    },
    {
        "epoch": 9,
        "n_train": 48,
        "n_val": 3,
        "ns_start": 3398433001154,
        "ns_end": 3398744112502,
        "train_loss": 52.47230911254883,
        "val_loss": 3.2696257829666138,
        "train_precision": 0.2883948602106193,
        "train_recall": 0.41375,
        "train_f1": 0.3206103797967409,
        "val_precision": 0.6312692000797925,
        "val_recall": 0.41333333333333333,
        "val_f1": 0.2785921760607839
    },
    {
        "epoch": 10,
        "n_train": 48,
        "n_val": 3,
        "ns_start": 3398760476379,
        "ns_end": 3399071997878,
        "train_loss": 52.25403070449829,
        "val_loss": 3.250940442085266,
        "train_precision": 0.35890985110771567,
        "train_recall": 0.44083333333333335,
        "train_f1": 0.35079305721871906,
        "val_precision": 0.36001697530864196,
        "val_recall": 0.4166666666666667,
        "val_f1": 0.2929827281277115
    },
    {
        "epoch": 11,
        "n_train": 48,
        "n_val": 3,
        "ns_start": 3399088647541,
        "ns_end": 3399399121733,
        "train_loss": 51.963797211647034,
        "val_loss": 3.2295548915863037,
        "train_precision": 0.39061619696302685,
        "train_recall": 0.456875,
        "train_f1": 0.37500747876193097,
        "val_precision": 0.31388070935147955,
        "val_recall": 0.4216666666666667,
        "val_f1": 0.3012501044350305
    },
    {
        "epoch": 12,
        "n_train": 48,
        "n_val": 3,
        "ns_start": 3399415978119,
        "ns_end": 3399720506758,
        "train_loss": 51.623326659202576,
        "val_loss": 3.207379460334778,
        "train_precision": 0.4412132563170268,
        "train_recall": 0.48052083333333334,
        "train_f1": 0.421533541978162,
        "val_precision": 0.32557520115730454,
        "val_recall": 0.42,
        "val_f1": 0.30525772323693195
    },
    {
        "epoch": 13,
        "n_train": 48,
        "n_val": 3,
        "ns_start": 3399737583445,
        "ns_end": 3400039240217,
        "train_loss": 51.25572872161865,
        "val_loss": 3.1847708225250244,
        "train_precision": 0.45881042549496426,
        "train_recall": 0.5002083333333334,
        "train_f1": 0.4568653096995217,
        "val_precision": 0.3092695722356739,
        "val_recall": 0.41,
        "val_f1": 0.2994805785029815
    },
    {
        "epoch": 14,
        "n_train": 48,
        "n_val": 3,
        "ns_start": 3400056358209,
        "ns_end": 3400359226929,
        "train_loss": 50.87318480014801,
        "val_loss": 3.160680055618286,
        "train_precision": 0.4853390501537072,
        "train_recall": 0.5179166666666667,
        "train_f1": 0.4841728161867142,
        "val_precision": 0.3212940917107584,
        "val_recall": 0.4066666666666667,
        "val_f1": 0.30002281416555204
    },
    {
        "epoch": 15,
        "n_train": 48,
        "n_val": 3,
        "ns_start": 3400376609782,
        "ns_end": 3400691871622,
        "train_loss": 50.47779667377472,
        "val_loss": 3.1347711086273193,
        "train_precision": 0.5124974270935913,
        "train_recall": 0.538125,
        "train_f1": 0.5120462729380012,
        "val_precision": 0.31278377725710593,
        "val_recall": 0.4,
        "val_f1": 0.2995626762125992
    },
    {
        "epoch": 16,
        "n_train": 48,
        "n_val": 3,
        "ns_start": 3400708938646,
        "ns_end": 3401011413848,
        "train_loss": 50.072235107421875,
        "val_loss": 3.1073758006095886,
        "train_precision": 0.5346259405489414,
        "train_recall": 0.5554166666666667,
        "train_f1": 0.5348399597711775,
        "val_precision": 0.3497382099316087,
        "val_recall": 0.415,
        "val_f1": 0.3251128887846459
    },
    {
        "epoch": 17,
        "n_train": 48,
        "n_val": 3,
        "ns_start": 3401029761714,
        "ns_end": 3401401828509,
        "train_loss": 49.660030484199524,
        "val_loss": 3.0789536833763123,
        "train_precision": 0.5457962561136401,
        "train_recall": 0.5638541666666667,
        "train_f1": 0.5462548463382954,
        "val_precision": 0.4015005368195024,
        "val_recall": 0.44666666666666666,
        "val_f1": 0.3743907497494454
    },
    {
        "epoch": 18,
        "n_train": 48,
        "n_val": 3,
        "ns_start": 3401418949847,
        "ns_end": 3401720714281,
        "train_loss": 49.24437773227692,
        "val_loss": 3.0499340295791626,
        "train_precision": 0.5541604590051443,
        "train_recall": 0.570625,
        "train_f1": 0.5547217896104515,
        "val_precision": 0.42926489778047444,
        "val_recall": 0.4716666666666667,
        "val_f1": 0.4114458200304722
    },
    {
        "epoch": 19,
        "n_train": 48,
        "n_val": 3,
        "ns_start": 3401737915172,
        "ns_end": 3402057833616,
        "train_loss": 48.82811200618744,
        "val_loss": 3.020663857460022,
        "train_precision": 0.5587294982052028,
        "train_recall": 0.5742708333333333,
        "train_f1": 0.5593109830335429,
        "val_precision": 0.47552606499452577,
        "val_recall": 0.5083333333333333,
        "val_f1": 0.4612049170627146
    },
    {
        "epoch": 20,
        "n_train": 48,
        "n_val": 3,
        "ns_start": 3402075525237,
        "ns_end": 3402376764475,
        "train_loss": 48.41375809907913,
        "val_loss": 2.9914625883102417,
        "train_precision": 0.5656501169679932,
        "train_recall": 0.5802083333333333,
        "train_f1": 0.566200839665421,
        "val_precision": 0.4791757831758764,
        "val_recall": 0.5183333333333333,
        "val_f1": 0.474097374181885
    },
    {
        "epoch": 21,
        "n_train": 48,
        "n_val": 3,
        "ns_start": 3402394082603,
        "ns_end": 3402707906509,
        "train_loss": 48.003537237644196,
        "val_loss": 2.962472379207611,
        "train_precision": 0.573544467749598,
        "train_recall": 0.5872916666666667,
        "train_f1": 0.5739337922053409,
        "val_precision": 0.5230439358063668,
        "val_recall": 0.5566666666666666,
        "val_f1": 0.5141066985610607
    },
    {
        "epoch": 22,
        "n_train": 48,
        "n_val": 3,
        "ns_start": 3402725047647,
        "ns_end": 3403038365564,
        "train_loss": 47.59925436973572,
        "val_loss": 2.9339189529418945,
        "train_precision": 0.5809886281859475,
        "train_recall": 0.5940625,
        "train_f1": 0.5823009348281258,
        "val_precision": 0.5643303571428572,
        "val_recall": 0.5833333333333334,
        "val_f1": 0.5412345679012346
    },
    {
        "epoch": 23,
        "n_train": 48,
        "n_val": 3,
        "ns_start": 3403055619774,
        "ns_end": 3403356734739,
        "train_loss": 47.20254725217819,
        "val_loss": 2.9058900475502014,
        "train_precision": 0.5907319468410624,
        "train_recall": 0.6021875,
        "train_f1": 0.592345287293688,
        "val_precision": 0.5587027320854603,
        "val_recall": 0.5883333333333334,
        "val_f1": 0.546368843192428
    },
    {
        "epoch": 24,
        "n_train": 48,
        "n_val": 3,
        "ns_start": 3403374035614,
        "ns_end": 3403686161621,
        "train_loss": 46.81464385986328,
        "val_loss": 2.8784728050231934,
        "train_precision": 0.5945295302530733,
        "train_recall": 0.605625,
        "train_f1": 0.596052431154518,
        "val_precision": 0.5842087053813899,
        "val_recall": 0.6066666666666667,
        "val_f1": 0.5642063272922094
    },
    {
        "epoch": 25,
        "n_train": 48,
        "n_val": 3,
        "ns_start": 3403703681433,
        "ns_end": 3404006527073,
        "train_loss": 46.4365411400795,
        "val_loss": 2.8517247438430786,
        "train_precision": 0.5964810202578572,
        "train_recall": 0.6069791666666666,
        "train_f1": 0.5979702008500726,
        "val_precision": 0.5869038461538462,
        "val_recall": 0.6183333333333333,
        "val_f1": 0.573907568602909
    },
    {
        "epoch": 26,
        "n_train": 48,
        "n_val": 3,
        "ns_start": 3404023885727,
        "ns_end": 3404324995689,
        "train_loss": 46.06900042295456,
        "val_loss": 2.8256857991218567,
        "train_precision": 0.5967641861760313,
        "train_recall": 0.6069791666666666,
        "train_f1": 0.5983254371653447,
        "val_precision": 0.5860569650385772,
        "val_recall": 0.625,
        "val_f1": 0.5800080650553271
    },
    {
        "epoch": 27,
        "n_train": 48,
        "n_val": 3,
        "ns_start": 3404342317487,
        "ns_end": 3404643929579,
        "train_loss": 45.71259397268295,
        "val_loss": 2.80037921667099,
        "train_precision": 0.595972945196422,
        "train_recall": 0.6060416666666667,
        "train_f1": 0.5976222292828807,
        "val_precision": 0.5972518629427577,
        "val_recall": 0.6333333333333333,
        "val_f1": 0.5878989144252097
    },
    {
        "epoch": 28,
        "n_train": 48,
        "n_val": 3,
        "ns_start": 3404661233567,
        "ns_end": 3404962721516,
        "train_loss": 45.367730021476746,
        "val_loss": 2.775820255279541,
        "train_precision": 0.5965833091705327,
        "train_recall": 0.6063541666666666,
        "train_f1": 0.5982005188144338,
        "val_precision": 0.5908044662309367,
        "val_recall": 0.635,
        "val_f1": 0.5853185407430627
    },
    {
        "epoch": 29,
        "n_train": 48,
        "n_val": 3,
        "ns_start": 3404980004089,
        "ns_end": 3405292957826,
        "train_loss": 45.03469377756119,
        "val_loss": 2.7520052790641785,
        "train_precision": 0.5990424128476548,
        "train_recall": 0.6083333333333333,
        "train_f1": 0.600665300627238,
        "val_precision": 0.5624719302436694,
        "val_recall": 0.6333333333333333,
        "val_f1": 0.5778063439162098
    },
    {
        "epoch": 30,
        "n_train": 48,
        "n_val": 3,
        "ns_start": 3405310143140,
        "ns_end": 3405612596395,
        "train_loss": 44.71364778280258,
        "val_loss": 2.728939652442932,
        "train_precision": 0.6023562916619888,
        "train_recall": 0.6111458333333334,
        "train_f1": 0.6038705454929681,
        "val_precision": 0.5134966727162735,
        "val_recall": 0.63,
        "val_f1": 0.5657083886186054
    },
    {
        "epoch": 31,
        "n_train": 48,
        "n_val": 3,
        "ns_start": 3405629819820,
        "ns_end": 3405944202608,
        "train_loss": 44.40469992160797,
        "val_loss": 2.7066144347190857,
        "train_precision": 0.6058375357642589,
        "train_recall": 0.6141666666666666,
        "train_f1": 0.6073089563985298,
        "val_precision": 0.5204148391812866,
        "val_recall": 0.635,
        "val_f1": 0.5717855676509426
    },
    {
        "epoch": 32,
        "n_train": 48,
        "n_val": 3,
        "ns_start": 3405961508397,
        "ns_end": 3406273939691,
        "train_loss": 44.1078696846962,
        "val_loss": 2.6850253343582153,
        "train_precision": 0.6075732237807088,
        "train_recall": 0.6155208333333333,
        "train_f1": 0.6090683393347424,
        "val_precision": 0.5269437602627259,
        "val_recall": 0.6383333333333333,
        "val_f1": 0.576907959181143
    },
    {
        "epoch": 33,
        "n_train": 48,
        "n_val": 3,
        "ns_start": 3406291019515,
        "ns_end": 3406592767967,
        "train_loss": 43.82312285900116,
        "val_loss": 2.664171278476715,
        "train_precision": 0.6104041224239724,
        "train_recall": 0.6177083333333333,
        "train_f1": 0.6118049547482,
        "val_precision": 0.5323030661539978,
        "val_recall": 0.6433333333333333,
        "val_f1": 0.5819232114029802
    },
    {
        "epoch": 34,
        "n_train": 48,
        "n_val": 3,
        "ns_start": 3406609886335,
        "ns_end": 3406926024895,
        "train_loss": 43.55035483837128,
        "val_loss": 2.644058883190155,
        "train_precision": 0.6107507500908704,
        "train_recall": 0.6177083333333333,
        "train_f1": 0.6120874261555247,
        "val_precision": 0.5335389375219883,
        "val_recall": 0.6416666666666667,
        "val_f1": 0.5818320263878516
    },
    {
        "epoch": 35,
        "n_train": 48,
        "n_val": 3,
        "ns_start": 3406943501439,
        "ns_end": 3407316455722,
        "train_loss": 43.28937256336212,
        "val_loss": 2.624701142311096,
        "train_precision": 0.6125594920576578,
        "train_recall": 0.6191666666666666,
        "train_f1": 0.6138447533378989,
        "val_precision": 0.5456400616926932,
        "val_recall": 0.6633333333333333,
        "val_f1": 0.596799513189343
    },
    {
        "epoch": 36,
        "n_train": 48,
        "n_val": 3,
        "ns_start": 3407333657978,
        "ns_end": 3407644050560,
        "train_loss": 43.03986740112305,
        "val_loss": 2.606110990047455,
        "train_precision": 0.6137132570319667,
        "train_recall": 0.6202083333333334,
        "train_f1": 0.6150712663938575,
        "val_precision": 0.5595543903107192,
        "val_recall": 0.6933333333333334,
        "val_f1": 0.6156761827118822
    },
    {
        "epoch": 37,
        "n_train": 48,
        "n_val": 3,
        "ns_start": 3407661326073,
        "ns_end": 3407962790415,
        "train_loss": 42.80143803358078,
        "val_loss": 2.588292717933655,
        "train_precision": 0.6137431753406972,
        "train_recall": 0.62,
        "train_f1": 0.6150865785747218,
        "val_precision": 0.5625713738997321,
        "val_recall": 0.7,
        "val_f1": 0.6197706791880099
    },
    {
        "epoch": 38,
        "n_train": 48,
        "n_val": 3,
        "ns_start": 3407980234094,
        "ns_end": 3408296987507,
        "train_loss": 42.57363152503967,
        "val_loss": 2.5712373852729797,
        "train_precision": 0.6137537191018315,
        "train_recall": 0.6197916666666666,
        "train_f1": 0.6150895185693965,
        "val_precision": 0.5672683918528652,
        "val_recall": 0.7083333333333334,
        "val_f1": 0.6253418289085545
    },
    {
        "epoch": 39,
        "n_train": 48,
        "n_val": 3,
        "ns_start": 3408314497596,
        "ns_end": 3408617137403,
        "train_loss": 42.35599756240845,
        "val_loss": 2.5549246668815613,
        "train_precision": 0.6137927852499853,
        "train_recall": 0.6195833333333334,
        "train_f1": 0.6150817833781552,
        "val_precision": 0.5728365041797522,
        "val_recall": 0.715,
        "val_f1": 0.6304369338832081
    },
    {
        "epoch": 40,
        "n_train": 48,
        "n_val": 3,
        "ns_start": 3408634658195,
        "ns_end": 3408936479594,
        "train_loss": 42.148123025894165,
        "val_loss": 2.539327561855316,
        "train_precision": 0.6156365219332951,
        "train_recall": 0.6210416666666667,
        "train_f1": 0.6168280453932137,
        "val_precision": 0.5728365041797522,
        "val_recall": 0.715,
        "val_f1": 0.6304369338832081
    },
    {
        "epoch": 41,
        "n_train": 48,
        "n_val": 3,
        "ns_start": 3408954137685,
        "ns_end": 3409256542982,
        "train_loss": 41.94962352514267,
        "val_loss": 2.5244175791740417,
        "train_precision": 0.6168895101296439,
        "train_recall": 0.621875,
        "train_f1": 0.6180051145922271,
        "val_precision": 0.5735081234598838,
        "val_recall": 0.715,
        "val_f1": 0.6306463351463352
    },
    {
        "epoch": 42,
        "n_train": 48,
        "n_val": 3,
        "ns_start": 3409274246549,
        "ns_end": 3409576080072,
        "train_loss": 41.76013767719269,
        "val_loss": 2.510165572166443,
        "train_precision": 0.6187478687234748,
        "train_recall": 0.6233333333333333,
        "train_f1": 0.6198115899782788,
        "val_precision": 0.5735081234598838,
        "val_recall": 0.715,
        "val_f1": 0.6306463351463352
    },
    {
        "epoch": 43,
        "n_train": 48,
        "n_val": 3,
        "ns_start": 3409593596169,
        "ns_end": 3409907678094,
        "train_loss": 41.57932037115097,
        "val_loss": 2.4965428709983826,
        "train_precision": 0.6203591743231648,
        "train_recall": 0.6247916666666666,
        "train_f1": 0.6214540301845008,
        "val_precision": 0.5735081234598838,
        "val_recall": 0.715,
        "val_f1": 0.6306463351463352
    },
    {
        "epoch": 44,
        "n_train": 48,
        "n_val": 3,
        "ns_start": 3409925218896,
        "ns_end": 3410227125918,
        "train_loss": 41.40683811903,
        "val_loss": 2.483522355556488,
        "train_precision": 0.6211949408273952,
        "train_recall": 0.6255208333333333,
        "train_f1": 0.6222596041794497,
        "val_precision": 0.5735081234598838,
        "val_recall": 0.715,
        "val_f1": 0.6306463351463352
    },
    {
        "epoch": 45,
        "n_train": 48,
        "n_val": 3,
        "ns_start": 3410244860922,
        "ns_end": 3410555970764,
        "train_loss": 41.24236589670181,
        "val_loss": 2.4710779786109924,
        "train_precision": 0.6220646115989421,
        "train_recall": 0.6263541666666667,
        "train_f1": 0.6231722339253679,
        "val_precision": 0.5735081234598838,
        "val_recall": 0.715,
        "val_f1": 0.6306463351463352
    },
    {
        "epoch": 46,
        "n_train": 48,
        "n_val": 3,
        "ns_start": 3410573440189,
        "ns_end": 3410885044254,
        "train_loss": 41.08558338880539,
        "val_loss": 2.4591845273971558,
        "train_precision": 0.6236050230068712,
        "train_recall": 0.6279166666666667,
        "train_f1": 0.6248031172257213,
        "val_precision": 0.5735081234598838,
        "val_recall": 0.715,
        "val_f1": 0.6306463351463352
    },
    {
        "epoch": 47,
        "n_train": 48,
        "n_val": 3,
        "ns_start": 3410902504942,
        "ns_end": 3411205116274,
        "train_loss": 40.93617856502533,
        "val_loss": 2.447817862033844,
        "train_precision": 0.6243392984081471,
        "train_recall": 0.6286458333333333,
        "train_f1": 0.6255582247517294,
        "val_precision": 0.5735081234598838,
        "val_recall": 0.715,
        "val_f1": 0.6306463351463352
    },
    {
        "epoch": 48,
        "n_train": 48,
        "n_val": 3,
        "ns_start": 3411222503382,
        "ns_end": 3411536766493,
        "train_loss": 40.79384309053421,
        "val_loss": 2.4369548559188843,
        "train_precision": 0.6265615665145818,
        "train_recall": 0.6309375,
        "train_f1": 0.627934612744172,
        "val_precision": 0.5735081234598838,
        "val_recall": 0.715,
        "val_f1": 0.6306463351463352
    },
    {
        "epoch": 49,
        "n_train": 48,
        "n_val": 3,
        "ns_start": 3411554300988,
        "ns_end": 3411857102425,
        "train_loss": 40.65828090906143,
        "val_loss": 2.4265741109848022,
        "train_precision": 0.6291484779775119,
        "train_recall": 0.6335416666666667,
        "train_f1": 0.6306170835079125,
        "val_precision": 0.5735081234598838,
        "val_recall": 0.715,
        "val_f1": 0.6306463351463352
    },
    {
        "epoch": 50,
        "n_train": 48,
        "n_val": 3,
        "ns_start": 3411874633230,
        "ns_end": 3412177040035,
        "train_loss": 40.52920311689377,
        "val_loss": 2.4166548252105713,
        "train_precision": 0.6297087303310579,
        "train_recall": 0.6341666666666667,
        "train_f1": 0.6312733382983907,
        "val_precision": 0.5735081234598838,
        "val_recall": 0.715,
        "val_f1": 0.6306463351463352
    },
    {
        "epoch": 51,
        "n_train": 48,
        "n_val": 3,
        "ns_start": 3412194750452,
        "ns_end": 3412496528331,
        "train_loss": 40.4063161611557,
        "val_loss": 2.4071748852729797,
        "train_precision": 0.6297768722354233,
        "train_recall": 0.6342708333333333,
        "train_f1": 0.6313934590856155,
        "val_precision": 0.5735081234598838,
        "val_recall": 0.715,
        "val_f1": 0.6306463351463352
    },
    {
        "epoch": 52,
        "n_train": 48,
        "n_val": 3,
        "ns_start": 3412514153928,
        "ns_end": 3412815826629,
        "train_loss": 40.28934621810913,
        "val_loss": 2.3981159925460815,
        "train_precision": 0.6300260274024193,
        "train_recall": 0.6345833333333334,
        "train_f1": 0.6317342120086477,
        "val_precision": 0.5735081234598838,
        "val_recall": 0.715,
        "val_f1": 0.6306463351463352
    },
    {
        "epoch": 53,
        "n_train": 48,
        "n_val": 3,
        "ns_start": 3412833394178,
        "ns_end": 3413151092559,
        "train_loss": 40.178027749061584,
        "val_loss": 2.3894598484039307,
        "train_precision": 0.6308354369728681,
        "train_recall": 0.6354166666666666,
        "train_f1": 0.6325940461194176,
        "val_precision": 0.5735081234598838,
        "val_recall": 0.715,
        "val_f1": 0.6306463351463352
    },
    {
        "epoch": 54,
        "n_train": 48,
        "n_val": 3,
        "ns_start": 3413168643719,
        "ns_end": 3413478730352,
        "train_loss": 40.072096049785614,
        "val_loss": 2.3811874985694885,
        "train_precision": 0.6316361577129428,
        "train_recall": 0.63625,
        "train_f1": 0.6334528980591245,
        "val_precision": 0.5735081234598838,
        "val_recall": 0.715,
        "val_f1": 0.6306463351463352
    },
    {
        "epoch": 55,
        "n_train": 48,
        "n_val": 3,
        "ns_start": 3413496327603,
        "ns_end": 3413804755608,
        "train_loss": 39.9712975025177,
        "val_loss": 2.3732818365097046,
        "train_precision": 0.6335980771387648,
        "train_recall": 0.6382291666666666,
        "train_f1": 0.6354740063147833,
        "val_precision": 0.5735081234598838,
        "val_recall": 0.715,
        "val_f1": 0.6306463351463352
    },
    {
        "epoch": 56,
        "n_train": 48,
        "n_val": 3,
        "ns_start": 3413822273647,
        "ns_end": 3414123556200,
        "train_loss": 39.875390112400055,
        "val_loss": 2.365726947784424,
        "train_precision": 0.63397735741051,
        "train_recall": 0.6386458333333334,
        "train_f1": 0.6359012597785626,
        "val_precision": 0.5735081234598838,
        "val_recall": 0.715,
        "val_f1": 0.6306463351463352
    },
    {
        "epoch": 57,
        "n_train": 48,
        "n_val": 3,
        "ns_start": 3414141108512,
        "ns_end": 3414451832367,
        "train_loss": 39.784134805202484,
        "val_loss": 2.358506143093109,
        "train_precision": 0.6331635993686328,
        "train_recall": 0.6379166666666667,
        "train_f1": 0.6351633610023002,
        "val_precision": 0.5735081234598838,
        "val_recall": 0.715,
        "val_f1": 0.6306463351463352
    },
    {
        "epoch": 58,
        "n_train": 48,
        "n_val": 3,
        "ns_start": 3414470007738,
        "ns_end": 3414779254440,
        "train_loss": 39.697300374507904,
        "val_loss": 2.3516048192977905,
        "train_precision": 0.6343165851778878,
        "train_recall": 0.6390625,
        "train_f1": 0.6363242849728313,
        "val_precision": 0.5735081234598838,
        "val_recall": 0.715,
        "val_f1": 0.6306463351463352
    },
    {
        "epoch": 59,
        "n_train": 48,
        "n_val": 3,
        "ns_start": 3414796802243,
        "ns_end": 3415098625003,
        "train_loss": 39.61467009782791,
        "val_loss": 2.34500789642334,
        "train_precision": 0.636171286260252,
        "train_recall": 0.6409375,
        "train_f1": 0.6382190430895366,
        "val_precision": 0.5735081234598838,
        "val_recall": 0.715,
        "val_f1": 0.6306463351463352
    },
    {
        "epoch": 60,
        "n_train": 48,
        "n_val": 3,
        "ns_start": 3415116342068,
        "ns_end": 3415417817741,
        "train_loss": 39.53602796792984,
        "val_loss": 2.3387023210525513,
        "train_precision": 0.6375004980368946,
        "train_recall": 0.6422916666666667,
        "train_f1": 0.6395855048236528,
        "val_precision": 0.5735081234598838,
        "val_recall": 0.715,
        "val_f1": 0.6306463351463352
    },
    {
        "epoch": 61,
        "n_train": 48,
        "n_val": 3,
        "ns_start": 3415435366219,
        "ns_end": 3415738644103,
        "train_loss": 39.46116501092911,
        "val_loss": 2.332673966884613,
        "train_precision": 0.6376472297453872,
        "train_recall": 0.6425,
        "train_f1": 0.6397838305443004,
        "val_precision": 0.5735081234598838,
        "val_recall": 0.715,
        "val_f1": 0.6306463351463352
    },
    {
        "epoch": 62,
        "n_train": 48,
        "n_val": 3,
        "ns_start": 3415756328662,
        "ns_end": 3416065955623,
        "train_loss": 39.38988280296326,
        "val_loss": 2.32691091299057,
        "train_precision": 0.6381234215110838,
        "train_recall": 0.6430208333333334,
        "train_f1": 0.6402949791810671,
        "val_precision": 0.5735081234598838,
        "val_recall": 0.715,
        "val_f1": 0.6306463351463352
    },
    {
        "epoch": 63,
        "n_train": 48,
        "n_val": 3,
        "ns_start": 3416083521216,
        "ns_end": 3416390126374,
        "train_loss": 39.3219912648201,
        "val_loss": 2.3214011192321777,
        "train_precision": 0.6383170222362686,
        "train_recall": 0.6432291666666666,
        "train_f1": 0.6404997754792386,
        "val_precision": 0.5735081234598838,
        "val_recall": 0.715,
        "val_f1": 0.6306463351463352
    },
    {
        "epoch": 64,
        "n_train": 48,
        "n_val": 3,
        "ns_start": 3416407635405,
        "ns_end": 3416719146465,
        "train_loss": 39.25729411840439,
        "val_loss": 2.316134035587311,
        "train_precision": 0.6390028490957033,
        "train_recall": 0.6439583333333333,
        "train_f1": 0.6412149020714917,
        "val_precision": 0.5735081234598838,
        "val_recall": 0.715,
        "val_f1": 0.6306463351463352
    },
    {
        "epoch": 65,
        "n_train": 48,
        "n_val": 3,
        "ns_start": 3416736717404,
        "ns_end": 3417040559473,
        "train_loss": 39.19560772180557,
        "val_loss": 2.3110981583595276,
        "train_precision": 0.6392556721450141,
        "train_recall": 0.6442708333333333,
        "train_f1": 0.6414981435887177,
        "val_precision": 0.5735081234598838,
        "val_recall": 0.715,
        "val_f1": 0.6306463351463352
    },
    {
        "epoch": 66,
        "n_train": 48,
        "n_val": 3,
        "ns_start": 3417058096422,
        "ns_end": 3417359757250,
        "train_loss": 39.136743247509,
        "val_loss": 2.306283950805664,
        "train_precision": 0.6391273384668189,
        "train_recall": 0.6440625,
        "train_f1": 0.6413382090570415,
        "val_precision": 0.5735081234598838,
        "val_recall": 0.715,
        "val_f1": 0.6306463351463352
    },
    {
        "epoch": 67,
        "n_train": 48,
        "n_val": 3,
        "ns_start": 3417377235990,
        "ns_end": 3417686031639,
        "train_loss": 39.080518305301666,
        "val_loss": 2.3016826510429382,
        "train_precision": 0.6393800914760307,
        "train_recall": 0.644375,
        "train_f1": 0.6416065786743633,
        "val_precision": 0.5735081234598838,
        "val_recall": 0.715,
        "val_f1": 0.6306463351463352
    },
    {
        "epoch": 68,
        "n_train": 48,
        "n_val": 3,
        "ns_start": 3417703490528,
        "ns_end": 3418012473105,
        "train_loss": 39.02673989534378,
        "val_loss": 2.2972845435142517,
        "train_precision": 0.6397854454873372,
        "train_recall": 0.6447916666666667,
        "train_f1": 0.6420101885757928,
        "val_precision": 0.5735081234598838,
        "val_recall": 0.715,
        "val_f1": 0.6306463351463352
    },
    {
        "epoch": 69,
        "n_train": 48,
        "n_val": 3,
        "ns_start": 3418029972632,
        "ns_end": 3418331590974,
        "train_loss": 38.97521132230759,
        "val_loss": 2.293082058429718,
        "train_precision": 0.6401745903802587,
        "train_recall": 0.6452083333333334,
        "train_f1": 0.642397273496412,
        "val_precision": 0.5735081234598838,
        "val_recall": 0.715,
        "val_f1": 0.6306463351463352
    },
    {
        "epoch": 70,
        "n_train": 48,
        "n_val": 3,
        "ns_start": 3418349196522,
        "ns_end": 3418662218517,
        "train_loss": 38.9257293343544,
        "val_loss": 2.289066731929779,
        "train_precision": 0.6402357899400777,
        "train_recall": 0.6453125,
        "train_f1": 0.6424558434865032,
        "val_precision": 0.5735081234598838,
        "val_recall": 0.715,
        "val_f1": 0.6306463351463352
    },
    {
        "epoch": 71,
        "n_train": 48,
        "n_val": 3,
        "ns_start": 3418679616628,
        "ns_end": 3418982359207,
        "train_loss": 38.878079533576965,
        "val_loss": 2.285230040550232,
        "train_precision": 0.6406279926631225,
        "train_recall": 0.6457291666666667,
        "train_f1": 0.6428361348547268,
        "val_precision": 0.5735081234598838,
        "val_recall": 0.715,
        "val_f1": 0.6306463351463352
    },
    {
        "epoch": 72,
        "n_train": 48,
        "n_val": 3,
        "ns_start": 3418999826816,
        "ns_end": 3419316157622,
        "train_loss": 38.83205050230026,
        "val_loss": 2.2815619111061096,
        "train_precision": 0.6411411518764086,
        "train_recall": 0.64625,
        "train_f1": 0.6433354786503193,
        "val_precision": 0.5735081234598838,
        "val_recall": 0.715,
        "val_f1": 0.6306463351463352
    },
    {
        "epoch": 73,
        "n_train": 48,
        "n_val": 3,
        "ns_start": 3419333663167,
        "ns_end": 3419635577275,
        "train_loss": 38.787444829940796,
        "val_loss": 2.278052031993866,
        "train_precision": 0.6426077775504148,
        "train_recall": 0.6477083333333333,
        "train_f1": 0.6447669212991551,
        "val_precision": 0.5735081234598838,
        "val_recall": 0.715,
        "val_f1": 0.6306463351463352
    },
    {
        "epoch": 74,
        "n_train": 48,
        "n_val": 3,
        "ns_start": 3419653149557,
        "ns_end": 3419957996304,
        "train_loss": 38.74410545825958,
        "val_loss": 2.274687349796295,
        "train_precision": 0.6428994287322791,
        "train_recall": 0.6480208333333334,
        "train_f1": 0.6450373106721524,
        "val_precision": 0.5735081234598838,
        "val_recall": 0.715,
        "val_f1": 0.6306463351463352
    },
    {
        "epoch": 75,
        "n_train": 48,
        "n_val": 3,
        "ns_start": 3419975478364,
        "ns_end": 3420284278731,
        "train_loss": 38.701925337314606,
        "val_loss": 2.271455705165863,
        "train_precision": 0.6448877856965735,
        "train_recall": 0.65,
        "train_f1": 0.6469556507663683,
        "val_precision": 0.5735081234598838,
        "val_recall": 0.715,
        "val_f1": 0.6306463351463352
    },
    {
        "epoch": 76,
        "n_train": 48,
        "n_val": 3,
        "ns_start": 3420301762009,
        "ns_end": 3420612613647,
        "train_loss": 38.66086286306381,
        "val_loss": 2.2683441638946533,
        "train_precision": 0.6457420324059513,
        "train_recall": 0.6508333333333334,
        "train_f1": 0.6477926263961316,
        "val_precision": 0.5735081234598838,
        "val_recall": 0.715,
        "val_f1": 0.6306463351463352
    },
    {
        "epoch": 77,
        "n_train": 48,
        "n_val": 3,
        "ns_start": 3420630003476,
        "ns_end": 3420938267554,
        "train_loss": 38.620919942855835,
        "val_loss": 2.265342652797699,
        "train_precision": 0.6465848054682529,
        "train_recall": 0.6516666666666666,
        "train_f1": 0.6486048273661826,
        "val_precision": 0.5735081234598838,
        "val_recall": 0.715,
        "val_f1": 0.6306463351463352
    },
    {
        "epoch": 78,
        "n_train": 48,
        "n_val": 3,
        "ns_start": 3420955867856,
        "ns_end": 3421269866346,
        "train_loss": 38.58212226629257,
        "val_loss": 2.2624436616897583,
        "train_precision": 0.6468936365314464,
        "train_recall": 0.6519791666666667,
        "train_f1": 0.6488921952077258,
        "val_precision": 0.5735081234598838,
        "val_recall": 0.715,
        "val_f1": 0.6306463351463352
    },
    {
        "epoch": 79,
        "n_train": 48,
        "n_val": 3,
        "ns_start": 3421287421107,
        "ns_end": 3421591403693,
        "train_loss": 38.54449051618576,
        "val_loss": 2.2596399188041687,
        "train_precision": 0.6476352310162281,
        "train_recall": 0.6527083333333333,
        "train_f1": 0.6495813011888348,
        "val_precision": 0.5735081234598838,
        "val_recall": 0.715,
        "val_f1": 0.6306463351463352
    },
    {
        "epoch": 80,
        "n_train": 48,
        "n_val": 3,
        "ns_start": 3421608947769,
        "ns_end": 3421915348451,
        "train_loss": 38.50803655385971,
        "val_loss": 2.256927013397217,
        "train_precision": 0.6482805976146225,
        "train_recall": 0.6533333333333333,
        "train_f1": 0.6501859564702372,
        "val_precision": 0.5735081234598838,
        "val_recall": 0.715,
        "val_f1": 0.6306463351463352
    },
    {
        "epoch": 81,
        "n_train": 48,
        "n_val": 3,
        "ns_start": 3421932739982,
        "ns_end": 3422250038706,
        "train_loss": 38.472751557826996,
        "val_loss": 2.2543009519577026,
        "train_precision": 0.648489570970354,
        "train_recall": 0.6535416666666667,
        "train_f1": 0.6503790724740247,
        "val_precision": 0.5735081234598838,
        "val_recall": 0.715,
        "val_f1": 0.6306463351463352
    },
    {
        "epoch": 82,
        "n_train": 48,
        "n_val": 3,
        "ns_start": 3422267508742,
        "ns_end": 3422581746580,
        "train_loss": 38.43861472606659,
        "val_loss": 2.251757323741913,
        "train_precision": 0.6498792611033682,
        "train_recall": 0.6548958333333333,
        "train_f1": 0.6517295925641,
        "val_precision": 0.5735081234598838,
        "val_recall": 0.715,
        "val_f1": 0.6306463351463352
    },
    {
        "epoch": 83,
        "n_train": 48,
        "n_val": 3,
        "ns_start": 3422599141913,
        "ns_end": 3422902913881,
        "train_loss": 38.40559184551239,
        "val_loss": 2.249293327331543,
        "train_precision": 0.6499880604642667,
        "train_recall": 0.655,
        "train_f1": 0.6518398917284738,
        "val_precision": 0.5735081234598838,
        "val_recall": 0.715,
        "val_f1": 0.6306463351463352
    },
    {
        "epoch": 84,
        "n_train": 48,
        "n_val": 3,
        "ns_start": 3422920335936,
        "ns_end": 3423231827160,
        "train_loss": 38.37364840507507,
        "val_loss": 2.2469062209129333,
        "train_precision": 0.6497759195144158,
        "train_recall": 0.6547916666666667,
        "train_f1": 0.651637800454176,
        "val_precision": 0.5735081234598838,
        "val_recall": 0.715,
        "val_f1": 0.6306463351463352
    },
    {
        "epoch": 85,
        "n_train": 48,
        "n_val": 3,
        "ns_start": 3423249347925,
        "ns_end": 3423555657602,
        "train_loss": 38.342733681201935,
        "val_loss": 2.244593024253845,
        "train_precision": 0.6501023727456493,
        "train_recall": 0.6551041666666667,
        "train_f1": 0.6519685053117156,
        "val_precision": 0.5735081234598838,
        "val_recall": 0.715,
        "val_f1": 0.6306463351463352
    },
    {
        "epoch": 86,
        "n_train": 48,
        "n_val": 3,
        "ns_start": 3423573212766,
        "ns_end": 3423882694648,
        "train_loss": 38.31280595064163,
        "val_loss": 2.242350935935974,
        "train_precision": 0.6507414963645255,
        "train_recall": 0.6557291666666667,
        "train_f1": 0.6525841373365446,
        "val_precision": 0.5735081234598838,
        "val_recall": 0.715,
        "val_f1": 0.6306463351463352
    },
    {
        "epoch": 87,
        "n_train": 48,
        "n_val": 3,
        "ns_start": 3423900247125,
        "ns_end": 3424205192311,
        "train_loss": 38.283816277980804,
        "val_loss": 2.240177571773529,
        "train_precision": 0.6510760120882015,
        "train_recall": 0.6559375,
        "train_f1": 0.6528344156543905,
        "val_precision": 0.5735081234598838,
        "val_recall": 0.715,
        "val_f1": 0.6306463351463352
    },
    {
        "epoch": 88,
        "n_train": 48,
        "n_val": 3,
        "ns_start": 3424222859976,
        "ns_end": 3424528683409,
        "train_loss": 38.255721271038055,
        "val_loss": 2.238070487976074,
        "train_precision": 0.6515033130269802,
        "train_recall": 0.6563541666666667,
        "train_f1": 0.6532475450281383,
        "val_precision": 0.5735081234598838,
        "val_recall": 0.715,
        "val_f1": 0.6306463351463352
    },
    {
        "epoch": 89,
        "n_train": 48,
        "n_val": 3,
        "ns_start": 3424546247814,
        "ns_end": 3424852615734,
        "train_loss": 38.228470146656036,
        "val_loss": 2.236027419567108,
        "train_precision": 0.6521477726045419,
        "train_recall": 0.6569791666666667,
        "train_f1": 0.6538813528283818,
        "val_precision": 0.5735081234598838,
        "val_recall": 0.715,
        "val_f1": 0.6306463351463352
    },
    {
        "epoch": 90,
        "n_train": 48,
        "n_val": 3,
        "ns_start": 3424870213421,
        "ns_end": 3425226674720,
        "train_loss": 38.202021181583405,
        "val_loss": 2.2340463995933533,
        "train_precision": 0.6536376136894286,
        "train_recall": 0.6584375,
        "train_f1": 0.6552929695045384,
        "val_precision": 0.5735081234598838,
        "val_recall": 0.715,
        "val_f1": 0.6306463351463352
    },
    {
        "epoch": 91,
        "n_train": 48,
        "n_val": 3,
        "ns_start": 3425246156574,
        "ns_end": 3425568019801,
        "train_loss": 38.17632859945297,
        "val_loss": 2.2321245670318604,
        "train_precision": 0.6539573322340395,
        "train_recall": 0.65875,
        "train_f1": 0.6555951201273911,
        "val_precision": 0.5735081234598838,
        "val_recall": 0.715,
        "val_f1": 0.6306463351463352
    },
    {
        "epoch": 92,
        "n_train": 48,
        "n_val": 3,
        "ns_start": 3425585593500,
        "ns_end": 3425888289165,
        "train_loss": 38.15135568380356,
        "val_loss": 2.2302610278129578,
        "train_precision": 0.6540639425480496,
        "train_recall": 0.6588541666666666,
        "train_f1": 0.6556958106260855,
        "val_precision": 0.5735081234598838,
        "val_recall": 0.715,
        "val_f1": 0.6306463351463352
    },
    {
        "epoch": 93,
        "n_train": 48,
        "n_val": 3,
        "ns_start": 3425905976001,
        "ns_end": 3426209156355,
        "train_loss": 38.127059280872345,
        "val_loss": 2.228453278541565,
        "train_precision": 0.6545972782985935,
        "train_recall": 0.659375,
        "train_f1": 0.6561990660005176,
        "val_precision": 0.5735081234598838,
        "val_recall": 0.715,
        "val_f1": 0.6306463351463352
    },
    {
        "epoch": 94,
        "n_train": 48,
        "n_val": 3,
        "ns_start": 3426226723298,
        "ns_end": 3426538638381,
        "train_loss": 38.103415727615356,
        "val_loss": 2.2266986966133118,
        "train_precision": 0.6548107465401654,
        "train_recall": 0.6595833333333333,
        "train_f1": 0.6564002764507054,
        "val_precision": 0.5735081234598838,
        "val_recall": 0.715,
        "val_f1": 0.6306463351463352
    },
    {
        "epoch": 95,
        "n_train": 48,
        "n_val": 3,
        "ns_start": 3426556756357,
        "ns_end": 3426861510290,
        "train_loss": 38.08032524585724,
        "val_loss": 2.224998354911804,
        "train_precision": 0.6545956997897973,
        "train_recall": 0.659375,
        "train_f1": 0.6561889613070664,
        "val_precision": 0.5735081234598838,
        "val_recall": 0.715,
        "val_f1": 0.6306463351463352
    },
    {
        "epoch": 96,
        "n_train": 48,
        "n_val": 3,
        "ns_start": 3426879375294,
        "ns_end": 3427189942374,
        "train_loss": 38.05785781145096,
        "val_loss": 2.2233479022979736,
        "train_precision": 0.6541723031943321,
        "train_recall": 0.6589583333333333,
        "train_f1": 0.6558064198402395,
        "val_precision": 0.5735081234598838,
        "val_recall": 0.715,
        "val_f1": 0.6306463351463352
    },
    {
        "epoch": 97,
        "n_train": 48,
        "n_val": 3,
        "ns_start": 3427207614628,
        "ns_end": 3427516624533,
        "train_loss": 38.03589975833893,
        "val_loss": 2.22174608707428,
        "train_precision": 0.655355472583047,
        "train_recall": 0.6601041666666667,
        "train_f1": 0.6569735012868351,
        "val_precision": 0.5735081234598838,
        "val_recall": 0.715,
        "val_f1": 0.6306463351463352
    },
    {
        "epoch": 98,
        "n_train": 48,
        "n_val": 3,
        "ns_start": 3427534355655,
        "ns_end": 3427842608025,
        "train_loss": 38.01443839073181,
        "val_loss": 2.2201918959617615,
        "train_precision": 0.6560019901287643,
        "train_recall": 0.6607291666666667,
        "train_f1": 0.6576172046965975,
        "val_precision": 0.5735081234598838,
        "val_recall": 0.715,
        "val_f1": 0.6306463351463352
    },
    {
        "epoch": 99,
        "n_train": 48,
        "n_val": 3,
        "ns_start": 3427860249414,
        "ns_end": 3428166549998,
        "train_loss": 37.99344176054001,
        "val_loss": 2.2186843752861023,
        "train_precision": 0.6555704342806101,
        "train_recall": 0.6603125,
        "train_f1": 0.657184799120491,
        "val_precision": 0.5735081234598838,
        "val_recall": 0.715,
        "val_f1": 0.6306463351463352
    }
]