[
    {
        "epoch": 0,
        "n_train": 32,
        "n_val": 11,
        "ns_start": 293182712865394,
        "ns_end": 293188828942754,
        "train_loss": 14.570531532168388,
        "val_loss": 4.155341483652592,
        "train_precision": 0.8242082361124926,
        "train_recall": 0.8239791666666667,
        "train_f1": 0.8238823584401693,
        "val_precision": 0.8592167876081793,
        "val_recall": 0.859,
        "val_f1": 0.8590101013097869
    },
    {
        "epoch": 1,
        "n_train": 32,
        "n_val": 11,
        "ns_start": 293188862380169,
        "ns_end": 293194917600777,
        "train_loss": 11.191530480980873,
        "val_loss": 3.288619615137577,
        "train_precision": 0.866192120997293,
        "train_recall": 0.86396875,
        "train_f1": 0.8636416518123852,
        "val_precision": 0.8759742184994785,
        "val_recall": 0.8756363636363637,
        "val_f1": 0.8755668283907256
    },
    {
        "epoch": 2,
        "n_train": 32,
        "n_val": 11,
        "ns_start": 293194950729872,
        "ns_end": 293201120195118,
        "train_loss": 9.759959131479263,
        "val_loss": 2.860877089202404,
        "train_precision": 0.8854902738485637,
        "train_recall": 0.8841145833333334,
        "train_f1": 0.8839346767432644,
        "val_precision": 0.8826496949100179,
        "val_recall": 0.8816969696969696,
        "val_f1": 0.8815607364773651
    },
    {
        "epoch": 3,
        "n_train": 32,
        "n_val": 11,
        "ns_start": 293201152782802,
        "ns_end": 293207279042884,
        "train_loss": 8.783255062997341,
        "val_loss": 2.6670796051621437,
        "train_precision": 0.883960344381802,
        "train_recall": 0.8818020833333333,
        "train_f1": 0.8815384700949198,
        "val_precision": 0.882586103424935,
        "val_recall": 0.882090909090909,
        "val_f1": 0.882006872533965
    },
    {
        "epoch": 4,
        "n_train": 32,
        "n_val": 11,
        "ns_start": 293207312408084,
        "ns_end": 293213381003482,
        "train_loss": 8.31316039711237,
        "val_loss": 2.6109220571815968,
        "train_precision": 0.8831692759631008,
        "train_recall": 0.881625,
        "train_f1": 0.8814224776790514,
        "val_precision": 0.8818824968555101,
        "val_recall": 0.8816666666666667,
        "val_f1": 0.881618298167198
    },
    {
        "epoch": 5,
        "n_train": 32,
        "n_val": 11,
        "ns_start": 293213414474523,
        "ns_end": 293219505309606,
        "train_loss": 7.56954700499773,
        "val_loss": 2.5730412118136883,
        "train_precision": 0.8946778592942647,
        "train_recall": 0.89284375,
        "train_f1": 0.8926402704999118,
        "val_precision": 0.8862607362259413,
        "val_recall": 0.8855757575757576,
        "val_f1": 0.8854738591721962
    },
    {
        "epoch": 6,
        "n_train": 32,
        "n_val": 11,
        "ns_start": 293219540391196,
        "ns_end": 293225642645006,
        "train_loss": 7.391622990369797,
        "val_loss": 2.5709203872829676,
        "train_precision": 0.8953871713542509,
        "train_recall": 0.8935833333333333,
        "train_f1": 0.893384319035983,
        "val_precision": 0.8851744657081724,
        "val_recall": 0.8837878787878788,
        "val_f1": 0.8836103082731074
    },
    {
        "epoch": 7,
        "n_train": 32,
        "n_val": 11,
        "ns_start": 293225676308479,
        "ns_end": 293231763214515,
        "train_loss": 7.202396787703037,
        "val_loss": 2.4571508541703224,
        "train_precision": 0.8968642625198312,
        "train_recall": 0.8951875,
        "train_f1": 0.8950033227288386,
        "val_precision": 0.8927417946104685,
        "val_recall": 0.8914545454545455,
        "val_f1": 0.8913013960086846
    },
    {
        "epoch": 8,
        "n_train": 32,
        "n_val": 11,
        "ns_start": 293231796200756,
        "ns_end": 293237945645529,
        "train_loss": 6.994329251348972,
        "val_loss": 2.5887352265417576,
        "train_precision": 0.9000423738900087,
        "train_recall": 0.8987083333333333,
        "train_f1": 0.898560950470711,
        "val_precision": 0.8896214303803781,
        "val_recall": 0.8857272727272727,
        "val_f1": 0.8853242996221629
    },
    {
        "epoch": 9,
        "n_train": 32,
        "n_val": 11,
        "ns_start": 293237973790576,
        "ns_end": 293244120145183,
        "train_loss": 6.756479565054178,
        "val_loss": 2.508595747873187,
        "train_precision": 0.9022247117774665,
        "train_recall": 0.90059375,
        "train_f1": 0.9004253493164969,
        "val_precision": 0.895964279934426,
        "val_recall": 0.8921212121212121,
        "val_f1": 0.891751375874712
    },
    {
        "epoch": 10,
        "n_train": 32,
        "n_val": 11,
        "ns_start": 293244147391035,
        "ns_end": 293250291558981,
        "train_loss": 6.938235014677048,
        "val_loss": 2.38812355697155,
        "train_precision": 0.9024823665503682,
        "train_recall": 0.9009583333333333,
        "train_f1": 0.9007994273962355,
        "val_precision": 0.9007194007166117,
        "val_recall": 0.8958484848484849,
        "val_f1": 0.8954160324060614
    },
    {
        "epoch": 11,
        "n_train": 32,
        "n_val": 11,
        "ns_start": 293250324152408,
        "ns_end": 293256477280346,
        "train_loss": 6.616285976022482,
        "val_loss": 2.3714776234701276,
        "train_precision": 0.8993294341396365,
        "train_recall": 0.89796875,
        "train_f1": 0.8978176872902889,
        "val_precision": 0.8976342176564163,
        "val_recall": 0.8959393939393939,
        "val_f1": 0.8957592357886854
    },
    {
        "epoch": 12,
        "n_train": 32,
        "n_val": 11,
        "ns_start": 293256509644481,
        "ns_end": 293262631553790,
        "train_loss": 6.421799927949905,
        "val_loss": 2.252687282860279,
        "train_precision": 0.8982280045969901,
        "train_recall": 0.89784375,
        "train_f1": 0.8977836995829472,
        "val_precision": 0.9013755880915845,
        "val_recall": 0.9003636363636364,
        "val_f1": 0.9002497457165871
    },
    {
        "epoch": 13,
        "n_train": 32,
        "n_val": 11,
        "ns_start": 293262665323784,
        "ns_end": 293268773645519,
        "train_loss": 6.379077140241861,
        "val_loss": 2.50456624571234,
        "train_precision": 0.9048384685143337,
        "train_recall": 0.9043541666666667,
        "train_f1": 0.9042894549577227,
        "val_precision": 0.8940344868398238,
        "val_recall": 0.8898181818181818,
        "val_f1": 0.889407136146842
    },
    {
        "epoch": 14,
        "n_train": 32,
        "n_val": 11,
        "ns_start": 293268801902472,
        "ns_end": 293274873217157,
        "train_loss": 6.627422407269478,
        "val_loss": 3.7931489162147045,
        "train_precision": 0.9031542619097069,
        "train_recall": 0.9022291666666666,
        "train_f1": 0.9021226296887765,
        "val_precision": 0.8520531357836804,
        "val_recall": 0.8503333333333334,
        "val_f1": 0.850254907830214
    },
    {
        "epoch": 15,
        "n_train": 32,
        "n_val": 11,
        "ns_start": 293274901998557,
        "ns_end": 293281018427268,
        "train_loss": 7.104037303477526,
        "val_loss": 2.106078177690506,
        "train_precision": 0.8976698314626399,
        "train_recall": 0.8974895833333333,
        "train_f1": 0.8974527317906527,
        "val_precision": 0.9068015339863681,
        "val_recall": 0.9065454545454545,
        "val_f1": 0.9065061250657706
    },
    {
        "epoch": 16,
        "n_train": 32,
        "n_val": 11,
        "ns_start": 293281050042004,
        "ns_end": 293287225576045,
        "train_loss": 6.804103173315525,
        "val_loss": 2.943050315603614,
        "train_precision": 0.9074687287564399,
        "train_recall": 0.9067916666666667,
        "train_f1": 0.9067120725354795,
        "val_precision": 0.8880200661884655,
        "val_recall": 0.8877878787878788,
        "val_f1": 0.8877408069577876
    },
    {
        "epoch": 17,
        "n_train": 32,
        "n_val": 11,
        "ns_start": 293287254000012,
        "ns_end": 293293413539697,
        "train_loss": 6.0953288823366165,
        "val_loss": 2.5847966242581606,
        "train_precision": 0.9158605693456915,
        "train_recall": 0.9156354166666667,
        "train_f1": 0.9156025262183648,
        "val_precision": 0.9076720631347713,
        "val_recall": 0.903090909090909,
        "val_f1": 0.9027161271762902
    },
    {
        "epoch": 18,
        "n_train": 32,
        "n_val": 11,
        "ns_start": 293293441913654,
        "ns_end": 293299598519092,
        "train_loss": 5.622904729098082,
        "val_loss": 2.4134735614061356,
        "train_precision": 0.9288248948541152,
        "train_recall": 0.9281666666666667,
        "train_f1": 0.9281100165879309,
        "val_precision": 0.8985992079362611,
        "val_recall": 0.8984242424242425,
        "val_f1": 0.8983899004638146
    },
    {
        "epoch": 19,
        "n_train": 32,
        "n_val": 11,
        "ns_start": 293299627164793,
        "ns_end": 293305758098381,
        "train_loss": 5.6343110874295235,
        "val_loss": 2.7343205846846104,
        "train_precision": 0.9258254336731944,
        "train_recall": 0.9258125,
        "train_f1": 0.9258065126437862,
        "val_precision": 0.8949934578601537,
        "val_recall": 0.8897575757575757,
        "val_f1": 0.8892627871031511
    },
    {
        "epoch": 20,
        "n_train": 32,
        "n_val": 11,
        "ns_start": 293305786901467,
        "ns_end": 293311943239720,
        "train_loss": 5.46232695505023,
        "val_loss": 2.543759621679783,
        "train_precision": 0.925601863641642,
        "train_recall": 0.9251979166666666,
        "train_f1": 0.9251559481033664,
        "val_precision": 0.892599972787299,
        "val_recall": 0.8924848484848484,
        "val_f1": 0.8924928154634205
    },
    {
        "epoch": 21,
        "n_train": 32,
        "n_val": 11,
        "ns_start": 293311971753098,
        "ns_end": 293318061799561,
        "train_loss": 6.019484501332045,
        "val_loss": 2.8040810115635395,
        "train_precision": 0.9179354843577072,
        "train_recall": 0.91753125,
        "train_f1": 0.917483925980879,
        "val_precision": 0.8938326836244161,
        "val_recall": 0.8938181818181818,
        "val_f1": 0.8938079273198721
    },
    {
        "epoch": 22,
        "n_train": 32,
        "n_val": 11,
        "ns_start": 293318090157678,
        "ns_end": 293324217810597,
        "train_loss": 6.311641529202461,
        "val_loss": 2.3536613760516047,
        "train_precision": 0.9002495253411427,
        "train_recall": 0.89990625,
        "train_f1": 0.899852090998365,
        "val_precision": 0.9067388359397321,
        "val_recall": 0.9062424242424243,
        "val_f1": 0.9061801627611146
    },
    {
        "epoch": 23,
        "n_train": 32,
        "n_val": 11,
        "ns_start": 293324246435686,
        "ns_end": 293330342331533,
        "train_loss": 5.515516277402639,
        "val_loss": 2.3477501422166824,
        "train_precision": 0.9291094727008082,
        "train_recall": 0.9288333333333333,
        "train_f1": 0.9288028529538797,
        "val_precision": 0.9094530270994032,
        "val_recall": 0.9063636363636364,
        "val_f1": 0.9061061101269867
    },
    {
        "epoch": 24,
        "n_train": 32,
        "n_val": 11,
        "ns_start": 293330370585046,
        "ns_end": 293336508914302,
        "train_loss": 5.5765182711184025,
        "val_loss": 2.691403206437826,
        "train_precision": 0.921989113939636,
        "train_recall": 0.9201145833333333,
        "train_f1": 0.9199709652871252,
        "val_precision": 0.8919737017102759,
        "val_recall": 0.8918484848484849,
        "val_f1": 0.8918179719049176
    },
    {
        "epoch": 25,
        "n_train": 32,
        "n_val": 11,
        "ns_start": 293336537374655,
        "ns_end": 293342647859875,
        "train_loss": 5.405787825584412,
        "val_loss": 2.1562045253813267,
        "train_precision": 0.9217602048183992,
        "train_recall": 0.9216458333333334,
        "train_f1": 0.9216261863124734,
        "val_precision": 0.9184477240278762,
        "val_recall": 0.9158787878787878,
        "val_f1": 0.915685027710329
    },
    {
        "epoch": 26,
        "n_train": 32,
        "n_val": 11,
        "ns_start": 293342675656681,
        "ns_end": 293348832370763,
        "train_loss": 4.64048407971859,
        "val_loss": 2.246578927151859,
        "train_precision": 0.9348654491793948,
        "train_recall": 0.9345625,
        "train_f1": 0.9345331632691556,
        "val_precision": 0.9114291178406605,
        "val_recall": 0.9082424242424243,
        "val_f1": 0.9079846886292362
    },
    {
        "epoch": 27,
        "n_train": 32,
        "n_val": 11,
        "ns_start": 293348859820790,
        "ns_end": 293355045708549,
        "train_loss": 4.990604370832443,
        "val_loss": 2.44478749204427,
        "train_precision": 0.9318824840647812,
        "train_recall": 0.9318333333333333,
        "train_f1": 0.9318231587964669,
        "val_precision": 0.9067613446672412,
        "val_recall": 0.9066969696969697,
        "val_f1": 0.9066799495825085
    },
    {
        "epoch": 28,
        "n_train": 32,
        "n_val": 11,
        "ns_start": 293355073227929,
        "ns_end": 293361239044694,
        "train_loss": 5.046756001189351,
        "val_loss": 2.2922769775614142,
        "train_precision": 0.9359437087603586,
        "train_recall": 0.9356770833333333,
        "train_f1": 0.935650707786305,
        "val_precision": 0.9100759747939332,
        "val_recall": 0.9092727272727272,
        "val_f1": 0.9091877732773594
    },
    {
        "epoch": 29,
        "n_train": 32,
        "n_val": 11,
        "ns_start": 293361266532129,
        "ns_end": 293367454094230,
        "train_loss": 5.369122436270118,
        "val_loss": 2.3337063090875745,
        "train_precision": 0.9328435149384379,
        "train_recall": 0.9325104166666667,
        "train_f1": 0.9324779507233293,
        "val_precision": 0.9186151109596015,
        "val_recall": 0.916969696969697,
        "val_f1": 0.9168369008873851
    },
    {
        "epoch": 30,
        "n_train": 32,
        "n_val": 11,
        "ns_start": 293367482480170,
        "ns_end": 293373606456810,
        "train_loss": 4.53670609369874,
        "val_loss": 2.312515292316675,
        "train_precision": 0.9471605773400736,
        "train_recall": 0.94671875,
        "train_f1": 0.9466887429182816,
        "val_precision": 0.9150525144623817,
        "val_recall": 0.9147272727272727,
        "val_f1": 0.9146861617313636
    },
    {
        "epoch": 31,
        "n_train": 32,
        "n_val": 11,
        "ns_start": 293373634854566,
        "ns_end": 293379733856215,
        "train_loss": 4.018167644739151,
        "val_loss": 2.7654049526900053,
        "train_precision": 0.9504171969587204,
        "train_recall": 0.9502291666666667,
        "train_f1": 0.9502136341850976,
        "val_precision": 0.885568373378205,
        "val_recall": 0.8851212121212121,
        "val_f1": 0.885124125028606
    },
    {
        "epoch": 32,
        "n_train": 32,
        "n_val": 11,
        "ns_start": 293379762342107,
        "ns_end": 293385841444903,
        "train_loss": 4.406766261905432,
        "val_loss": 2.4674525717273355,
        "train_precision": 0.9448295563512926,
        "train_recall": 0.9446041666666667,
        "train_f1": 0.9445843738809551,
        "val_precision": 0.910950297361257,
        "val_recall": 0.9095151515151515,
        "val_f1": 0.9093827784084543
    },
    {
        "epoch": 33,
        "n_train": 32,
        "n_val": 11,
        "ns_start": 293385870350493,
        "ns_end": 293391971440692,
        "train_loss": 4.184626959264278,
        "val_loss": 2.4555078828707337,
        "train_precision": 0.9508209775387283,
        "train_recall": 0.9504270833333334,
        "train_f1": 0.9504015902662271,
        "val_precision": 0.9151630708879938,
        "val_recall": 0.9147878787878788,
        "val_f1": 0.9147425541081765
    },
    {
        "epoch": 34,
        "n_train": 32,
        "n_val": 11,
        "ns_start": 293391999728101,
        "ns_end": 293398109030790,
        "train_loss": 4.358852976933122,
        "val_loss": 2.709122327156365,
        "train_precision": 0.9390476158166682,
        "train_recall": 0.9390416666666667,
        "train_f1": 0.9390383713583376,
        "val_precision": 0.9164523283613468,
        "val_recall": 0.9161515151515152,
        "val_f1": 0.9161133459959855
    },
    {
        "epoch": 35,
        "n_train": 32,
        "n_val": 11,
        "ns_start": 293398137264215,
        "ns_end": 293404264038680,
        "train_loss": 4.437276966869831,
        "val_loss": 2.2878117682412267,
        "train_precision": 0.9438468351888638,
        "train_recall": 0.9436666666666667,
        "train_f1": 0.9436492262214745,
        "val_precision": 0.9087321135492135,
        "val_recall": 0.907969696969697,
        "val_f1": 0.9078865208963152
    },
    {
        "epoch": 36,
        "n_train": 32,
        "n_val": 11,
        "ns_start": 293404292793927,
        "ns_end": 293410406341346,
        "train_loss": 3.4511274080723524,
        "val_loss": 2.4487810861319304,
        "train_precision": 0.9569372392474521,
        "train_recall": 0.95678125,
        "train_f1": 0.9567695259644697,
        "val_precision": 0.9139193065609511,
        "val_recall": 0.9134848484848485,
        "val_f1": 0.9134336621366809
    },
    {
        "epoch": 37,
        "n_train": 32,
        "n_val": 11,
        "ns_start": 293410435092102,
        "ns_end": 293416591182995,
        "train_loss": 3.985543802380562,
        "val_loss": 2.542622709646821,
        "train_precision": 0.9481410832846432,
        "train_recall": 0.9481354166666667,
        "train_f1": 0.9481328522702535,
        "val_precision": 0.9072889234752444,
        "val_recall": 0.9065454545454545,
        "val_f1": 0.9064622303196646
    },
    {
        "epoch": 38,
        "n_train": 32,
        "n_val": 11,
        "ns_start": 293416619769721,
        "ns_end": 293422730483957,
        "train_loss": 3.612285353243351,
        "val_loss": 2.1423724610358477,
        "train_precision": 0.9553947925832726,
        "train_recall": 0.9551354166666667,
        "train_f1": 0.9551183311619901,
        "val_precision": 0.9264974989791143,
        "val_recall": 0.9263636363636364,
        "val_f1": 0.9263444419939095
    },
    {
        "epoch": 39,
        "n_train": 32,
        "n_val": 11,
        "ns_start": 293422759228492,
        "ns_end": 293428872339327,
        "train_loss": 3.3959963135421276,
        "val_loss": 3.20801614318043,
        "train_precision": 0.9580509501079189,
        "train_recall": 0.958,
        "train_f1": 0.9579942326768939,
        "val_precision": 0.8946238008089179,
        "val_recall": 0.8943333333333333,
        "val_f1": 0.894339833884034
    }
]